setup.cfg
setup.py
sssh/__init__.py
sssh/__main__.py
sssh/db.py
sssh/ssher.py
sssh.egg-info/PKG-INFO
sssh.egg-info/SOURCES.txt
sssh.egg-info/dependency_links.txt
sssh.egg-info/entry_points.txt
sssh.egg-info/top_level.txt