Metadata-Version: 1.1
Name: sssh
Version: 0.6
Summary: Stop remembering all the hosts when using SSH
Home-page: https://github.com/phizaz/ssher
Author: Konpat Preechakul
Author-email: the.akita.ta@gmail.com
License: UNKNOWN
Download-URL: https://github.com/phizaz/ssher/tarball/0.6
Keywords: ssh
Platform: UNKNOWN
